[
  {
    "id": 1,
    "name": "John Doe",
    "image": "https://i.ibb.co/Kzfrv7D/555.jpg",
    "review": "Excellent resume builder! Highly recommended.",
    "star": 5
  },
  {
    "id": 2,
    "name": "Jane Smith",
    "image": "https://i.ibb.co/7QwQZHN/666.jpg",
    "review": "Easy to use and professional templates.",
    "star": 4
  },
  {
    "id": 3,
    "name": "Bob Johnson",
    "image": "https://i.ibb.co/HxJ117r/444.jpg",
    "review": "Great features for customizing resumes.",
    "star": 4.5
  },
  {
    "id": 4,
    "name": "Alice Brown",
    "image": "https://i.ibb.co/7QwQZHN/666.jpg",
    "review": "Helped me land my dream job!",
    "star": 5
  },
  {
    "id": 5,
    "name": "Michael White",
    "image": "https://i.ibb.co/YB29LNL/111.jpg",
    "review": "User-friendly interface and quick results.",
    "star": 4.7
  }
]
